Debugger/DebuggerGui.py
Debugger/__init__.py
robotframework_debugger-0.2.1.dist-info/LICENSE
robotframework_debugger-0.2.1.dist-info/METADATA
robotframework_debugger-0.2.1.dist-info/WHEEL
robotframework_debugger-0.2.1.dist-info/top_level.txt
robotframework_debugger-0.2.1.dist-info/RECORD
