Metadata-Version: 2.1
Name: robotframework-debugger
Version: 0.2.1
Summary: A Robot Framework Listener to try keywords and pause execution on failure
Home-page: https://github.com/Snooz82/robotframework-debugger
Author: René Rohner(Snooz82)
Author-email: snooz@posteo.de
License: UNKNOWN
Platform: UNKNOWN
Classifier: Programming Language :: Python :: 3
Classifier: Programming Language :: Python :: 3.6
Classifier: Programming Language :: Python :: 3.7
Classifier: License :: OSI Approved :: Apache Software License
Classifier: Operating System :: OS Independent
Classifier: Topic :: Software Development :: Testing
Classifier: Topic :: Software Development :: Testing :: Acceptance
Classifier: Framework :: Robot Framework
Requires-Python: >=3.6
Requires-Dist: robotframework (>=3.2.1)
